s6r_odoo/__init__.py
s6r_odoo/file_import.py
s6r_odoo/model.py
s6r_odoo/odoo.py
s6r_odoo/record.py
s6r_odoo/record_set.py
s6r_odoo-2.2.5.dist-info/licenses/LICENSE
s6r_odoo-2.2.5.dist-info/METADATA
s6r_odoo-2.2.5.dist-info/WHEEL
s6r_odoo-2.2.5.dist-info/top_level.txt
s6r_odoo-2.2.5.dist-info/RECORD
