Metadata-Version: 2.4
Name: s6r-odoo
Version: 2.2.5
Summary: Odoo RPC client
Author-email: Michel Perrocheau <michel@scalizer.fr>
License:                    GNU LESSER GENERAL PUBLIC LICENSE
Project-URL: Homepage, https://github.com/ScalizerOrg/s6r-odoo
Project-URL: Changelog, https://github.com/ScalizerOrg/s6r-odoo/blob/main/CHANGELOG.md
Keywords: odoo
Classifier: License :: OSI Approved :: GNU Lesser General Public License v3 (LGPLv3)
Classifier: Programming Language :: Python
Classifier: Programming Language :: Python :: 3
Requires-Python: >=3.9
License-File: LICENSE
Requires-Dist: beautifulsoup4==4.12.2
Requires-Dist: requests
Requires-Dist: xlrd==2.0.1
Requires-Dist: openpyxl==3.1.2
Provides-Extra: dev
Requires-Dist: twine; extra == "dev"
Requires-Dist: bumpver; extra == "dev"
Requires-Dist: pip-tools; extra == "dev"
Requires-Dist: pytest; extra == "dev"
Requires-Dist: check-manifest; extra == "dev"
Dynamic: license-file
